pyream/__init__.py
pyream/acdb.py
pyream/cd.py
pyream/cron.py
pyream/lru.py
pyream/objectdict.py
pyream/rate.py
pyream-0.1.2.dist-info/METADATA
pyream-0.1.2.dist-info/WHEEL
pyream-0.1.2.dist-info/licenses/LICENSE
pyream-0.1.2.dist-info/RECORD
