Metadata-Version: 2.4
Name: pyream
Version: 0.1.2
Summary: pyream: a utility library written in python
Project-URL: homepage, https://github.com/mohanson/pyream
Author-email: Mohanson <mohanson@outlook.com>
License: MIT License
License-File: LICENSE
